ibm_mq_cli/__init__.py
ibm_mq_cli/main.py
ibm_mq_cli-0.7.131.dist-info/LICENSE
ibm_mq_cli-0.7.131.dist-info/METADATA
ibm_mq_cli-0.7.131.dist-info/WHEEL
ibm_mq_cli-0.7.131.dist-info/entry_points.txt
ibm_mq_cli-0.7.131.dist-info/top_level.txt
ibm_mq_cli-0.7.131.dist-info/RECORD
