Metadata-Version: 2.1
Name: ibm-mq-cli
Version: 0.7.131
Summary: IBM MQ Management CLI Tool
Author-email: Brian Hartford <bh419@protonmail.com>
License: MIT License
Project-URL: homepage, https://github.com/UTXOnly/ibm_mq_cli
Classifier: Development Status :: 4 - Beta
Classifier: Intended Audience :: Developers
Classifier: Programming Language :: Python :: 3
Classifier: License :: OSI Approved :: MIT License
License-File: LICENSE
Requires-Dist: pexpect
